perchance/__init__.py
perchance/cli.py
perchance/runner.py
perchance/transform.py
perchance_dsl-0.1.1.dist-info/LICENSE
perchance_dsl-0.1.1.dist-info/METADATA
perchance_dsl-0.1.1.dist-info/WHEEL
perchance_dsl-0.1.1.dist-info/entry_points.txt
perchance_dsl-0.1.1.dist-info/top_level.txt
perchance_dsl-0.1.1.dist-info/RECORD
