Metadata-Version: 2.2
Name: perchance-dsl
Version: 0.1.1
Summary: A DSL for replacing if-else statements with a more readable syntax
Home-page: https://github.com/ehrev/perchance-dsl
Author: Ehre
Classifier: Programming Language :: Python :: 3
Classifier: License :: OSI Approved :: MIT License
Classifier: Operating System :: OS Independent
Requires-Python: >=3.6
License-File: LICENSE
Dynamic: author
Dynamic: classifier
Dynamic: description
Dynamic: description-content-type
Dynamic: home-page
Dynamic: requires-python
Dynamic: summary
